partialedge/__init__.py
partialedge/__main__.py
partialedge/config.py
partialedge/ped.py
partialedge/ped_crossing.py
partialedge/ped_tree.py
partialedge/ped_tree_decomposition.py
partialedge/algorithm/__init__.py
partialedge/algorithm/ped_algorithm.py
partialedge/algorithm/ped_run.py
partialedge/core/__init__.py
partialedge/core/crossing.py
partialedge/core/tree.py
partialedge/core/tree_decomp.py
partialedge/exception/__init__.py
partialedge/exception/ped_exception.py
partialedge/graph/__init__.py
partialedge/graph/graph_creation.py
partialedge/graph/graph_window.py
partialedge/resources/demo/dir/dir_set_0.json
partialedge/resources/demo/dir/dir_set_1.json
partialedge/resources/demo/dir/dir_set_2.json
partialedge/resources/demo/dir/dir_set_3.json
partialedge/resources/demo/dir/dir_set_4.json
partialedge/resources/demo/dir/out/dir_set_0.json
partialedge/resources/demo/dir/out/dir_set_1.json
partialedge/resources/demo/dir/out/dir_set_2.json
partialedge/resources/demo/dir/out/dir_set_3.json
partialedge/resources/demo/dir/out/dir_set_4.json
partialedge/resources/demo/dir/out/dir_set_0/result/graph_0.png
partialedge/resources/demo/dir/out/dir_set_0/result/graph_1.png
partialedge/resources/demo/dir/out/dir_set_0/result/graph_2.png
partialedge/resources/demo/dir/out/dir_set_0/result/graph_3.png
partialedge/resources/demo/dir/out/dir_set_0/result/graph_4.png
partialedge/resources/demo/dir/out/dir_set_0/result/graph_5.png
partialedge/resources/demo/dir/out/dir_set_0/result/graph_6.png
partialedge/resources/demo/dir/out/dir_set_0/result/graph_7.png
partialedge/resources/demo/dir/out/dir_set_0/result/graph_8.png
partialedge/resources/demo/dir/out/dir_set_0/result/graph_9.png
partialedge/resources/demo/dir/out/dir_set_0/source/graph_0.png
partialedge/resources/demo/dir/out/dir_set_0/source/graph_1.png
partialedge/resources/demo/dir/out/dir_set_0/source/graph_2.png
partialedge/resources/demo/dir/out/dir_set_0/source/graph_3.png
partialedge-1.0.1.dist-info/LICENSE.txt
partialedge-1.0.1.dist-info/METADATA
partialedge-1.0.1.dist-info/WHEEL
partialedge-1.0.1.dist-info/top_level.txt
partialedge-1.0.1.dist-info/RECORD
