Metadata-Version: 2.1
Name: partialedge
Version: 1.0.1
Summary: A collection of algorithms for solving Maximum Ink Partial Edge Drawing Problems
Home-page: https://bitbucket.org/Remvipomed/partialedgedrawing/src/master/
Author: Matthias Hummel
Author-email: matthiashummel@ymail.com
License: MIT
Keywords: maximum,ink,partial,edge,drawing,algorithm
Platform: UNKNOWN
Classifier: Development Status :: 5 - Production/Stable
Classifier: Intended Audience :: Science/Research
Classifier: Topic :: Scientific/Engineering
Classifier: Topic :: Scientific/Engineering :: Visualization
Classifier: License :: OSI Approved :: MIT License
Classifier: Programming Language :: Python :: 3
Classifier: Programming Language :: Python :: 3.7
License-File: LICENSE.txt
Requires-Dist: networkx (>=2)
Requires-Dist: treedecomp (>=1)
Requires-Dist: pygeos
Requires-Dist: matplotlib (>=3)
Requires-Dist: scipy (>=1)
